setup.cfg
setup.py
splicer/__init__.py
splicer/aggregate.py
splicer/ast.py
splicer/compat.py
splicer/dataset.py
splicer/field.py
splicer/immutable.py
splicer/operations.py
splicer/path.py
splicer/query.py
splicer/query_builder.py
splicer/query_parser.py
splicer/relation.py
splicer/schema.py
splicer/schema_interpreter.py
splicer/table.py
splicer.egg-info/PKG-INFO
splicer.egg-info/SOURCES.txt
splicer.egg-info/dependency_links.txt
splicer.egg-info/requires.txt
splicer.egg-info/top_level.txt
splicer/adapters/__init__.py
splicer/adapters/dict_adapter.py
splicer/adapters/dir_adapter.py
splicer/adapters/null_adapter.py
splicer/codecs/__init__.py
splicer/codecs/csv.py
splicer/compilers/__init__.py
splicer/compilers/join.py
splicer/compilers/local.py
splicer/functions/__init__.py
splicer/functions/aggregates.py
splicer/functions/filesystem.py
splicer/functions/math.py
splicer/functions/relational.py
splicer/functions/string.py
tests/__init__.py
tests/test_codec.py
tests/test_compiler.py
tests/test_dataset.py
tests/test_dict_adapter.py
tests/test_dir_adapter.py
tests/test_field.py
tests/test_filesystem.py
tests/test_join.py
tests/test_operations.py
tests/test_ops.py
tests/test_path.py
tests/test_query_builder.py
tests/test_query_parser.py
tests/test_schema.py
tests/test_schema_interpreter.py
tests/fixtures/__init__.py
tests/fixtures/employee_adapter.py
tests/fixtures/mock_adapter.py
tests/functional/__init__.py